[
  {
    "type": "Domain",
    "value": "htx.com"
  },
  {
    "type": "Domain",
    "value": "hbabit.com"
  },
  {
    "type": "Domain",
    "value": "hbfile.net"
  },
  {
    "type": "Domain",
    "value": "huobi.com"
  },
  {
    "type": "Domain",
    "value": "huobi.me"
  },
  {
    "type": "Domain",
    "value": "huobi.pro"
  },
  {
    "type": "Domain",
    "value": "huobi.sc"
  },
  {
    "type": "Domain",
    "value": "huobiasia.vip"
  },
  {
    "type": "Domain",
    "value": "huobigroup.com"
  },
  {
    "type": "Domain",
    "value": "huobitoken.com"
  }
]