[
  {
    "type": "Full",
    "value": "img-prod-cms-rt-microsoft-com.akamaized.net"
  },
  {
    "type": "Full",
    "value": "img-s-msn-com.akamaized.net"
  },
  {
    "type": "Full",
    "value": "mwf-service.akamaized.net"
  },
  {
    "type": "Full",
    "value": "officecdn-microsoft-com.akamaized.net"
  },
  {
    "type": "Full",
    "value": "statics-marketingsites-eas-ms-com.akamaized.net"
  },
  {
    "type": "Full",
    "value": "statics-marketingsites-eus-ms-com.akamaized.net"
  },
  {
    "type": "Full",
    "value": "statics-marketingsites-wcus-ms-com.akamaized.net"
  },
  {
    "type": "Full",
    "value": "crl.microsoft.com"
  },
  {
    "type": "Full",
    "value": "mscrl.microsoft.com"
  },
  {
    "type": "Full",
    "value": "ocsp.microsoft.com"
  },
  {
    "type": "Full",
    "value": "oneocsp.microsoft.com"
  },
  {
    "type": "Full",
    "value": "flightsimulator.azureedge.net"
  },
  {
    "type": "Full",
    "value": "prodforza.blob.core.windows.net"
  },
  {
    "type": "Full",
    "value": "azure.microsoft.com"
  },
  {
    "type": "Full",
    "value": "azuremarketplace.microsoft.com"
  },
  {
    "type": "Full",
    "value": "location.microsoft.com"
  },
  {
    "type": "Full",
    "value": "github-api.arkoselabs.com"
  },
  {
    "type": "Full",
    "value": "github-cloud.s3.amazonaws.com"
  },
  {
    "type": "Full",
    "value": "az764295.vo.msecnd.net"
  },
  {
    "type": "Full",
    "value": "bingsettingssearch.trafficmanager.net"
  },
  {
    "type": "Full",
    "value": "default.exp-tas.com"
  },
  {
    "type": "Full",
    "value": "developer.microsoft.com"
  },
  {
    "type": "Full",
    "value": "download.visualstudio.microsoft.com"
  },
  {
    "type": "Full",
    "value": "dtlgalleryint.cloudapp.net"
  },
  {
    "type": "Full",
    "value": "packages.microsoft.com"
  },
  {
    "type": "Full",
    "value": "poshtestgallery.cloudapp.net"
  },
  {
    "type": "Full",
    "value": "psg-int-centralus.cloudapp.net"
  },
  {
    "type": "Full",
    "value": "psg-int-eastus.cloudapp.net"
  },
  {
    "type": "Full",
    "value": "rink.hockeyapp.net"
  },
  {
    "type": "Full",
    "value": "vscode-sync-insiders.trafficmanager.net"
  },
  {
    "type": "Full",
    "value": "vscode-sync.trafficmanager.net"
  },
  {
    "type": "Full",
    "value": "vscode.blob.core.windows.net"
  },
  {
    "type": "Full",
    "value": "vscode.search.windows.net"
  },
  {
    "type": "Full",
    "value": "vsmarketplacebadge.apphb.com"
  },
  {
    "type": "Domain",
    "value": "microsoft"
  },
  {
    "type": "Domain",
    "value": "hotmail"
  },
  {
    "type": "Domain",
    "value": "office"
  },
  {
    "type": "Domain",
    "value": "skype"
  },
  {
    "type": "Domain",
    "value": "windows"
  },
  {
    "type": "Domain",
    "value": "bing"
  },
  {
    "type": "Domain",
    "value": "azure"
  },
  {
    "type": "Domain",
    "value": "xbox"
  },
  {
    "type": "Domain",
    "value": "winhec.net"
  },
  {
    "type": "Domain",
    "value": "mymicrosoft.com"
  },
  {
    "type": "Domain",
    "value": "microsoft.ch"
  },
  {
    "type": "Domain",
    "value": "microsoft.cl"
  },
  {
    "type": "Domain",
    "value": "microsoft.com"
  },
  {
    "type": "Domain",
    "value": "microsoft.cz"
  },
  {
    "type": "Domain",
    "value": "microsoft.de"
  },
  {
    "type": "Domain",
    "value": "microsoft.dk"
  },
  {
    "type": "Domain",
    "value": "microsoft.ee"
  },
  {
    "type": "Domain",
    "value": "microsoft.es"
  },
  {
    "type": "Domain",
    "value": "microsoft.eu"
  },
  {
    "type": "Domain",
    "value": "microsoft.fi"
  },
  {
    "type": "Domain",
    "value": "microsoft.ge"
  },
  {
    "type": "Domain",
    "value": "microsoft.hu"
  },
  {
    "type": "Domain",
    "value": "microsoft.io"
  },
  {
    "type": "Domain",
    "value": "microsoft.is"
  },
  {
    "type": "Domain",
    "value": "microsoft.it"
  },
  {
    "type": "Domain",
    "value": "microsoft.jp"
  },
  {
    "type": "Domain",
    "value": "microsoft.lt"
  },
  {
    "type": "Domain",
    "value": "microsoft.lu"
  },
  {
    "type": "Domain",
    "value": "microsoft.lv"
  },
  {
    "type": "Domain",
    "value": "microsoft.md"
  },
  {
    "type": "Domain",
    "value": "microsoft.net"
  },
  {
    "type": "Domain",
    "value": "microsoft.pl"
  },
  {
    "type": "Domain",
    "value": "microsoft.pt"
  },
  {
    "type": "Domain",
    "value": "microsoft.red"
  },
  {
    "type": "Domain",
    "value": "microsoft.ro"
  },
  {
    "type": "Domain",
    "value": "microsoft.rs"
  },
  {
    "type": "Domain",
    "value": "microsoft.ru"
  },
  {
    "type": "Domain",
    "value": "microsoft.se"
  },
  {
    "type": "Domain",
    "value": "microsoft.si"
  },
  {
    "type": "Domain",
    "value": "microsoft.tv"
  },
  {
    "type": "Domain",
    "value": "microsoft.ua"
  },
  {
    "type": "Domain",
    "value": "microsoft.uz"
  },
  {
    "type": "Domain",
    "value": "microsoft.vn"
  },
  {
    "type": "Domain",
    "value": "femalefounderscomp.com"
  },
  {
    "type": "Domain",
    "value": "m12.vc"
  },
  {
    "type": "Domain",
    "value": "a-msedge.net"
  },
  {
    "type": "Domain",
    "value": "aka.ms"
  },
  {
    "type": "Domain",
    "value": "ankarazirvesi2018.com"
  },
  {
    "type": "Domain",
    "value": "applicationinsights.io"
  },
  {
    "type": "Domain",
    "value": "applicationinsights.net"
  },
  {
    "type": "Domain",
    "value": "aria.ms"
  },
  {
    "type": "Domain",
    "value": "asp.net"
  },
  {
    "type": "Domain",
    "value": "aspnetcdn.com"
  },
  {
    "type": "Domain",
    "value": "binads.com"
  },
  {
    "type": "Domain",
    "value": "bluehatil.com"
  },
  {
    "type": "Domain",
    "value": "boswp.com"
  },
  {
    "type": "Domain",
    "value": "brazilpartneruniversity.com"
  },
  {
    "type": "Domain",
    "value": "breakdown.me"
  },
  {
    "type": "Domain",
    "value": "c-msedge.net"
  },
  {
    "type": "Domain",
    "value": "centralvalidation.com"
  },
  {
    "type": "Domain",
    "value": "ch9.ms"
  },
  {
    "type": "Domain",
    "value": "charticulator.com"
  },
  {
    "type": "Domain",
    "value": "cloudapp.net"
  },
  {
    "type": "Domain",
    "value": "cloudappsecurity.com"
  },
  {
    "type": "Domain",
    "value": "cortanaanalytics.com"
  },
  {
    "type": "Domain",
    "value": "cortanaskills.com"
  },
  {
    "type": "Domain",
    "value": "crmdynint-gcc.com"
  },
  {
    "type": "Domain",
    "value": "crmdynint.com"
  },
  {
    "type": "Domain",
    "value": "crossborderexpansion.com"
  },
  {
    "type": "Domain",
    "value": "docs.com"
  },
  {
    "type": "Domain",
    "value": "dynamics.com"
  },
  {
    "type": "Domain",
    "value": "efproject.net"
  },
  {
    "type": "Domain",
    "value": "fasttrackreadysupport.com"
  },
  {
    "type": "Domain",
    "value": "fluidpreview.com"
  },
  {
    "type": "Domain",
    "value": "footprintdns.com"
  },
  {
    "type": "Domain",
    "value": "gameuxmasterguide.com"
  },
  {
    "type": "Domain",
    "value": "gears5.com"
  },
  {
    "type": "Domain",
    "value": "gearspop.com"
  },
  {
    "type": "Domain",
    "value": "gearstactics.com"
  },
  {
    "type": "Domain",
    "value": "gfx.ms"
  },
  {
    "type": "Domain",
    "value": "gigjam.com"
  },
  {
    "type": "Domain",
    "value": "hololens.com"
  },
  {
    "type": "Domain",
    "value": "hotmail.co"
  },
  {
    "type": "Domain",
    "value": "hotmail.com"
  },
  {
    "type": "Domain",
    "value": "hotmail.eu"
  },
  {
    "type": "Domain",
    "value": "hotmail.net"
  },
  {
    "type": "Domain",
    "value": "hotmail.org"
  },
  {
    "type": "Domain",
    "value": "hummingbird.ms"
  },
  {
    "type": "Domain",
    "value": "ie10.com"
  },
  {
    "type": "Domain",
    "value": "ie11.com"
  },
  {
    "type": "Domain",
    "value": "ie8.co"
  },
  {
    "type": "Domain",
    "value": "ie9.com"
  },
  {
    "type": "Domain",
    "value": "imaginecup.pl"
  },
  {
    "type": "Domain",
    "value": "ingads.com"
  },
  {
    "type": "Domain",
    "value": "internetexplorer.co"
  },
  {
    "type": "Domain",
    "value": "internetexplorer.com"
  },
  {
    "type": "Domain",
    "value": "intunewiki.com"
  },
  {
    "type": "Domain",
    "value": "iotinactionevents.com"
  },
  {
    "type": "Domain",
    "value": "kidgrid.tv"
  },
  {
    "type": "Domain",
    "value": "kumo.com"
  },
  {
    "type": "Domain",
    "value": "l-msedge.net"
  },
  {
    "type": "Domain",
    "value": "latampartneruniversity.com"
  },
  {
    "type": "Domain",
    "value": "live.com"
  },
  {
    "type": "Domain",
    "value": "live.eu"
  },
  {
    "type": "Domain",
    "value": "live.net"
  },
  {
    "type": "Domain",
    "value": "livingyourambition.com"
  },
  {
    "type": "Domain",
    "value": "makecode.org"
  },
  {
    "type": "Domain",
    "value": "managedmeetingrooms.com"
  },
  {
    "type": "Domain",
    "value": "meetfasttrack.com"
  },
  {
    "type": "Domain",
    "value": "meetyourdevices.com"
  },
  {
    "type": "Domain",
    "value": "mepn.com"
  },
  {
    "type": "Domain",
    "value": "microsoftedgeinsider.com"
  },
  {
    "type": "Domain",
    "value": "microsoft-falcon.io"
  },
  {
    "type": "Domain",
    "value": "microsoft-int.com"
  },
  {
    "type": "Domain",
    "value": "microsoft-ppe.com"
  },
  {
    "type": "Domain",
    "value": "microsoft-sap-events.com"
  },
  {
    "type": "Domain",
    "value": "microsoft-sbs-domains.com"
  },
  {
    "type": "Domain",
    "value": "microsoft365.com"
  },
  {
    "type": "Domain",
    "value": "microsoftaccountguard.com"
  },
  {
    "type": "Domain",
    "value": "microsoftadvertising.com"
  },
  {
    "type": "Domain",
    "value": "microsoftadvertisingregionalawards.com"
  },
  {
    "type": "Domain",
    "value": "microsoftaffiliates.com"
  },
  {
    "type": "Domain",
    "value": "microsoftapp.net"
  },
  {
    "type": "Domain",
    "value": "microsoftcloud.com"
  },
  {
    "type": "Domain",
    "value": "microsoftcloudworkshop.com"
  },
  {
    "type": "Domain",
    "value": "microsoftcommunitytraining.com"
  },
  {
    "type": "Domain",
    "value": "microsoftedge.com"
  },
  {
    "type": "Domain",
    "value": "microsofthouse.com"
  },
  {
    "type": "Domain",
    "value": "microsofthouse.net"
  },
  {
    "type": "Domain",
    "value": "microsoftinternetsafety.net"
  },
  {
    "type": "Domain",
    "value": "microsoftlatamaitour.com"
  },
  {
    "type": "Domain",
    "value": "microsoftlinc.com"
  },
  {
    "type": "Domain",
    "value": "microsoftonline-p.com"
  },
  {
    "type": "Domain",
    "value": "microsoftonline.com"
  },
  {
    "type": "Domain",
    "value": "microsoftpartnercommunity.com"
  },
  {
    "type": "Domain",
    "value": "microsoftpersonalcontent.com"
  },
  {
    "type": "Domain",
    "value": "microsoftready.com"
  },
  {
    "type": "Domain",
    "value": "microsoftsiteselection.com"
  },
  {
    "type": "Domain",
    "value": "microsoftstore.com"
  },
  {
    "type": "Domain",
    "value": "microsoftstream.com"
  },
  {
    "type": "Domain",
    "value": "microsoftteams.com"
  },
  {
    "type": "Domain",
    "value": "microsofttradein.com"
  },
  {
    "type": "Domain",
    "value": "microsofttranslator.com"
  },
  {
    "type": "Domain",
    "value": "microsoftuwp.com"
  },
  {
    "type": "Domain",
    "value": "momentumms.com"
  },
  {
    "type": "Domain",
    "value": "morphcharts.com"
  },
  {
    "type": "Domain",
    "value": "mpnevolution.com"
  },
  {
    "type": "Domain",
    "value": "ms-studiosmedia.com"
  },
  {
    "type": "Domain",
    "value": "ms365surfaceoffer.com"
  },
  {
    "type": "Domain",
    "value": "msauth.net"
  },
  {
    "type": "Domain",
    "value": "mschallenge2018.com"
  },
  {
    "type": "Domain",
    "value": "msecnd.net"
  },
  {
    "type": "Domain",
    "value": "msedge.net"
  },
  {
    "type": "Domain",
    "value": "msft.info"
  },
  {
    "type": "Domain",
    "value": "msft.net"
  },
  {
    "type": "Domain",
    "value": "msftauth.net"
  },
  {
    "type": "Domain",
    "value": "msftauthimages.net"
  },
  {
    "type": "Domain",
    "value": "msftconnecttest.com"
  },
  {
    "type": "Domain",
    "value": "msfteducation.ca"
  },
  {
    "type": "Domain",
    "value": "msftncsi.com"
  },
  {
    "type": "Domain",
    "value": "msftnet.org"
  },
  {
    "type": "Domain",
    "value": "msgamesresearch.com"
  },
  {
    "type": "Domain",
    "value": "msgamestudios.com"
  },
  {
    "type": "Domain",
    "value": "mshome.net"
  },
  {
    "type": "Domain",
    "value": "msidentity.com"
  },
  {
    "type": "Domain",
    "value": "msocdn.com"
  },
  {
    "type": "Domain",
    "value": "msturing.org"
  },
  {
    "type": "Domain",
    "value": "msudalosti.com"
  },
  {
    "type": "Domain",
    "value": "xamarin.com"
  },
  {
    "type": "Domain",
    "value": "nextechafrica.net"
  },
  {
    "type": "Domain",
    "value": "nxta.org"
  },
  {
    "type": "Domain",
    "value": "o365weve-dev.com"
  },
  {
    "type": "Domain",
    "value": "o365weve-ppe.com"
  },
  {
    "type": "Domain",
    "value": "o365weve.com"
  },
  {
    "type": "Domain",
    "value": "office.com"
  },
  {
    "type": "Domain",
    "value": "office.net"
  },
  {
    "type": "Domain",
    "value": "office365.com"
  },
  {
    "type": "Domain",
    "value": "onenote.com"
  },
  {
    "type": "Domain",
    "value": "onenote.net"
  },
  {
    "type": "Domain",
    "value": "onestore.ms"
  },
  {
    "type": "Domain",
    "value": "opticsforthecloud.net"
  },
  {
    "type": "Domain",
    "value": "outingsapp.com"
  },
  {
    "type": "Domain",
    "value": "outlook.com"
  },
  {
    "type": "Domain",
    "value": "passport.net"
  },
  {
    "type": "Domain",
    "value": "pixapp.net"
  },
  {
    "type": "Domain",
    "value": "powerappscdn.net"
  },
  {
    "type": "Domain",
    "value": "powerautomate.com"
  },
  {
    "type": "Domain",
    "value": "powerbi.com"
  },
  {
    "type": "Domain",
    "value": "powershellgallery.com"
  },
  {
    "type": "Domain",
    "value": "projectmurphy.net"
  },
  {
    "type": "Domain",
    "value": "projectsangam.com"
  },
  {
    "type": "Domain",
    "value": "pxt.io"
  },
  {
    "type": "Domain",
    "value": "s-dc-msedge.net"
  },
  {
    "type": "Domain",
    "value": "s-microsoft.com"
  },
  {
    "type": "Domain",
    "value": "s-msedge.net"
  },
  {
    "type": "Domain",
    "value": "s-msft.com"
  },
  {
    "type": "Domain",
    "value": "s-msn.com"
  },
  {
    "type": "Domain",
    "value": "sfbassets.com"
  },
  {
    "type": "Domain",
    "value": "sfbassets.net"
  },
  {
    "type": "Domain",
    "value": "sfx.ms"
  },
  {
    "type": "Domain",
    "value": "sharepoint.com"
  },
  {
    "type": "Domain",
    "value": "sharepointonline.com"
  },
  {
    "type": "Domain",
    "value": "signalr.net"
  },
  {
    "type": "Domain",
    "value": "skype.com"
  },
  {
    "type": "Domain",
    "value": "skype.net"
  },
  {
    "type": "Domain",
    "value": "skypeassets.com"
  },
  {
    "type": "Domain",
    "value": "skypeassets.net"
  },
  {
    "type": "Domain",
    "value": "spo-msedge.net"
  },
  {
    "type": "Domain",
    "value": "staffhub.ms"
  },
  {
    "type": "Domain",
    "value": "successwithteams.com"
  },
  {
    "type": "Domain",
    "value": "surface.com"
  },
  {
    "type": "Domain",
    "value": "svc.ms"
  },
  {
    "type": "Domain",
    "value": "sway-cdn.com"
  },
  {
    "type": "Domain",
    "value": "sway.com"
  },
  {
    "type": "Domain",
    "value": "sysinternals.com"
  },
  {
    "type": "Domain",
    "value": "t-msedge.net"
  },
  {
    "type": "Domain",
    "value": "tailwindtraders.com"
  },
  {
    "type": "Domain",
    "value": "techhub.ms"
  },
  {
    "type": "Domain",
    "value": "microsoftnews.com"
  },
  {
    "type": "Domain",
    "value": "translatetheweb.com"
  },
  {
    "type": "Domain",
    "value": "unlocklimitlesslearning.com"
  },
  {
    "type": "Domain",
    "value": "userpxt.io"
  },
  {
    "type": "Domain",
    "value": "videobreakdown.com"
  },
  {
    "type": "Domain",
    "value": "videoindexer.ai"
  },
  {
    "type": "Domain",
    "value": "virtualearth.net"
  },
  {
    "type": "Domain",
    "value": "vsallin.net"
  },
  {
    "type": "Domain",
    "value": "wbd.ms"
  },
  {
    "type": "Domain",
    "value": "what-fan.net"
  },
  {
    "type": "Domain",
    "value": "windows-int.net"
  },
  {
    "type": "Domain",
    "value": "windows.com"
  },
  {
    "type": "Domain",
    "value": "windows.net"
  },
  {
    "type": "Domain",
    "value": "windows.nl"
  },
  {
    "type": "Domain",
    "value": "windows8.hk"
  },
  {
    "type": "Domain",
    "value": "windowscommunity.net"
  },
  {
    "type": "Domain",
    "value": "windowsmarketplace.com"
  },
  {
    "type": "Domain",
    "value": "windowsphone-int.com"
  },
  {
    "type": "Domain",
    "value": "windowsphone.com"
  },
  {
    "type": "Domain",
    "value": "windowssearch.com"
  },
  {
    "type": "Domain",
    "value": "windowsupdate.com"
  },
  {
    "type": "Domain",
    "value": "winhec.com"
  },
  {
    "type": "Domain",
    "value": "microsoft.ca"
  },
  {
    "type": "Domain",
    "value": "yammer.com"
  },
  {
    "type": "Domain",
    "value": "msocsp.com"
  },
  {
    "type": "Domain",
    "value": "microsoftnews.cc"
  },
  {
    "type": "Domain",
    "value": "azuredatabricks.net"
  },
  {
    "type": "Domain",
    "value": "microsoft.cat"
  },
  {
    "type": "Domain",
    "value": "tfsallin.net"
  },
  {
    "type": "Domain",
    "value": "microsoftnews.net"
  },
  {
    "type": "Domain",
    "value": "microsoftnews.org"
  },
  {
    "type": "Domain",
    "value": "microsoftnewsforkids.com"
  },
  {
    "type": "Domain",
    "value": "microsoftnewsforkids.net"
  },
  {
    "type": "Domain",
    "value": "microsoftnewsforkids.org"
  },
  {
    "type": "Domain",
    "value": "microsoftnewskids.com"
  },
  {
    "type": "Domain",
    "value": "microsoftnewskids.net"
  },
  {
    "type": "Domain",
    "value": "microsoftnewskids.org"
  },
  {
    "type": "Domain",
    "value": "msn.com"
  },
  {
    "type": "Domain",
    "value": "msnewskids.com"
  },
  {
    "type": "Domain",
    "value": "msnewskids.net"
  },
  {
    "type": "Domain",
    "value": "msnewskids.org"
  },
  {
    "type": "Domain",
    "value": "msnkids.com"
  },
  {
    "type": "Domain",
    "value": "microsoftstart.com"
  },
  {
    "type": "Domain",
    "value": "start.com"
  },
  {
    "type": "Domain",
    "value": "1drv.com"
  },
  {
    "type": "Domain",
    "value": "1drv.ms"
  },
  {
    "type": "Domain",
    "value": "livefilestore.com"
  },
  {
    "type": "Domain",
    "value": "onedrive.co"
  },
  {
    "type": "Domain",
    "value": "onedrive.com"
  },
  {
    "type": "Domain",
    "value": "onedrive.eu"
  },
  {
    "type": "Domain",
    "value": "onedrive.net"
  },
  {
    "type": "Domain",
    "value": "onedrive.org"
  },
  {
    "type": "Domain",
    "value": "vscode-unpkg.net"
  },
  {
    "type": "Domain",
    "value": "vscode-cdn.net"
  },
  {
    "type": "Domain",
    "value": "vscode.dev"
  },
  {
    "type": "Domain",
    "value": "vsassets.io"
  },
  {
    "type": "Domain",
    "value": "vfsforgit.org"
  },
  {
    "type": "Domain",
    "value": "microsoft.by"
  },
  {
    "type": "Domain",
    "value": "gamepass.com"
  },
  {
    "type": "Domain",
    "value": "orithegame.com"
  },
  {
    "type": "Domain",
    "value": "renovacionxboxlive.com"
  },
  {
    "type": "Domain",
    "value": "tellmewhygame.com"
  },
  {
    "type": "Domain",
    "value": "xbox.co"
  },
  {
    "type": "Domain",
    "value": "xbox.com"
  },
  {
    "type": "Domain",
    "value": "xbox.eu"
  },
  {
    "type": "Domain",
    "value": "xbox.org"
  },
  {
    "type": "Domain",
    "value": "xbox360.co"
  },
  {
    "type": "Domain",
    "value": "xbox360.com"
  },
  {
    "type": "Domain",
    "value": "xbox360.eu"
  },
  {
    "type": "Domain",
    "value": "xbox360.org"
  },
  {
    "type": "Domain",
    "value": "xboxab.com"
  },
  {
    "type": "Domain",
    "value": "xboxgamepass.com"
  },
  {
    "type": "Domain",
    "value": "xboxgamestudios.com"
  },
  {
    "type": "Domain",
    "value": "xboxlive.com"
  },
  {
    "type": "Domain",
    "value": "xboxone.co"
  },
  {
    "type": "Domain",
    "value": "xboxone.com"
  },
  {
    "type": "Domain",
    "value": "xboxone.eu"
  },
  {
    "type": "Domain",
    "value": "xboxplayanywhere.com"
  },
  {
    "type": "Domain",
    "value": "xboxservices.com"
  },
  {
    "type": "Domain",
    "value": "xboxstudios.com"
  },
  {
    "type": "Domain",
    "value": "xbx.lv"
  },
  {
    "type": "Domain",
    "value": "asobostudio.com"
  },
  {
    "type": "Domain",
    "value": "flightsimulator.com"
  },
  {
    "type": "Domain",
    "value": "beth.games"
  },
  {
    "type": "Domain",
    "value": "bethesda.net"
  },
  {
    "type": "Domain",
    "value": "bethesdagamestudios.com"
  },
  {
    "type": "Domain",
    "value": "bethsoft.com"
  },
  {
    "type": "Domain",
    "value": "doom.com"
  },
  {
    "type": "Domain",
    "value": "elderscrolls.com"
  },
  {
    "type": "Domain",
    "value": "forza.net"
  },
  {
    "type": "Domain",
    "value": "forzamotorsport.net"
  },
  {
    "type": "Domain",
    "value": "forzaracingchampionship.com"
  },
  {
    "type": "Domain",
    "value": "forzarc.com"
  },
  {
    "type": "Domain",
    "value": "callersbane.com"
  },
  {
    "type": "Domain",
    "value": "minecraft-services.net"
  },
  {
    "type": "Domain",
    "value": "minecraft.net"
  },
  {
    "type": "Domain",
    "value": "minecraftservices.com"
  },
  {
    "type": "Domain",
    "value": "minecraftshop.com"
  },
  {
    "type": "Domain",
    "value": "mojang.com"
  },
  {
    "type": "Domain",
    "value": "microsoft.be"
  },
  {
    "type": "Domain",
    "value": "aadrm.com"
  },
  {
    "type": "Domain",
    "value": "azure-devices-int.net"
  },
  {
    "type": "Domain",
    "value": "azure-devices.net"
  },
  {
    "type": "Domain",
    "value": "azure-mobile.net"
  },
  {
    "type": "Domain",
    "value": "azure-sphere.com"
  },
  {
    "type": "Domain",
    "value": "azure-test.net"
  },
  {
    "type": "Domain",
    "value": "azure.com"
  },
  {
    "type": "Domain",
    "value": "azure.net"
  },
  {
    "type": "Domain",
    "value": "azurecomcdn.net"
  },
  {
    "type": "Domain",
    "value": "azurecomm.net"
  },
  {
    "type": "Domain",
    "value": "azurecontainer.io"
  },
  {
    "type": "Domain",
    "value": "azurecosmos.net"
  },
  {
    "type": "Domain",
    "value": "azurecosmosdb.com"
  },
  {
    "type": "Domain",
    "value": "azurecosmosdb.info"
  },
  {
    "type": "Domain",
    "value": "azurecosmosdb.net"
  },
  {
    "type": "Domain",
    "value": "vfsforgit.com"
  },
  {
    "type": "Domain",
    "value": "azuredevopslaunch.com"
  },
  {
    "type": "Domain",
    "value": "azuredigitaltwin.com"
  },
  {
    "type": "Domain",
    "value": "azuredigitaltwins.com"
  },
  {
    "type": "Domain",
    "value": "azuredigitaltwins.net"
  },
  {
    "type": "Domain",
    "value": "azuredns-prd.info"
  },
  {
    "type": "Domain",
    "value": "azuredns-prd.org"
  },
  {
    "type": "Domain",
    "value": "azureedge-test.net"
  },
  {
    "type": "Domain",
    "value": "azureedge.net"
  },
  {
    "type": "Domain",
    "value": "azurefd.net"
  },
  {
    "type": "Domain",
    "value": "azureiotcentral.com"
  },
  {
    "type": "Domain",
    "value": "azureiotsolutions.com"
  },
  {
    "type": "Domain",
    "value": "azureiotsuite.com"
  },
  {
    "type": "Domain",
    "value": "azureplanetscale.info"
  },
  {
    "type": "Domain",
    "value": "azureplanetscale.net"
  },
  {
    "type": "Domain",
    "value": "azureserviceprofiler.com"
  },
  {
    "type": "Domain",
    "value": "azuresmartspaces.net"
  },
  {
    "type": "Domain",
    "value": "azurestackvalidation.com"
  },
  {
    "type": "Domain",
    "value": "azurewebsites.net"
  },
  {
    "type": "Domain",
    "value": "botframework.com"
  },
  {
    "type": "Domain",
    "value": "cosmosdb.info"
  },
  {
    "type": "Domain",
    "value": "cosmosdb.net"
  },
  {
    "type": "Domain",
    "value": "devopsms.com"
  },
  {
    "type": "Domain",
    "value": "gotcosmos.com"
  },
  {
    "type": "Domain",
    "value": "management-azure-devices-int.net"
  },
  {
    "type": "Domain",
    "value": "management-azure-devices.net"
  },
  {
    "type": "Domain",
    "value": "microsoftazuread-sso.com"
  },
  {
    "type": "Domain",
    "value": "microsoftazuresponsorships.com"
  },
  {
    "type": "Domain",
    "value": "microsofteca.com"
  },
  {
    "type": "Domain",
    "value": "microsoftiotcentral.com"
  },
  {
    "type": "Domain",
    "value": "msn.net"
  },
  {
    "type": "Domain",
    "value": "playfab.com"
  },
  {
    "type": "Domain",
    "value": "playfabapi.com"
  },
  {
    "type": "Domain",
    "value": "serverlesslibrary.net"
  },
  {
    "type": "Domain",
    "value": "trafficmanager.net"
  },
  {
    "type": "Domain",
    "value": "tryfunctions.com"
  },
  {
    "type": "Domain",
    "value": "windowsazure.com"
  },
  {
    "type": "Domain",
    "value": "azure-dns.com"
  },
  {
    "type": "Domain",
    "value": "azure-dns.info"
  },
  {
    "type": "Domain",
    "value": "azure-dns.net"
  },
  {
    "type": "Domain",
    "value": "azure-dns.org"
  },
  {
    "type": "Domain",
    "value": "microsoft.az"
  },
  {
    "type": "Domain",
    "value": "microsoftdiplomados.com"
  },
  {
    "type": "Domain",
    "value": "bing123.com"
  },
  {
    "type": "Domain",
    "value": "flipwithsurface.com"
  },
  {
    "type": "Domain",
    "value": "masalladeloslimites.com"
  },
  {
    "type": "Domain",
    "value": "bingapis.com"
  },
  {
    "type": "Domain",
    "value": "bingapistatistics.com"
  },
  {
    "type": "Domain",
    "value": "bingparachute.com"
  },
  {
    "type": "Domain",
    "value": "bingsandbox.com"
  },
  {
    "type": "Domain",
    "value": "bingvisualsearch.com"
  },
  {
    "type": "Domain",
    "value": "bingworld.com"
  },
  {
    "type": "Domain",
    "value": "bluehatnights.com"
  },
  {
    "type": "Domain",
    "value": "dictate.ms"
  },
  {
    "type": "Domain",
    "value": "sprinklesapp.com"
  },
  {
    "type": "Domain",
    "value": "bing.net"
  },
  {
    "type": "Domain",
    "value": "bingagencyawards.com"
  },
  {
    "type": "Domain",
    "value": "microsoft-give.com"
  },
  {
    "type": "Domain",
    "value": "microsoftcloudsummit.com"
  },
  {
    "type": "Domain",
    "value": "bing.com"
  },
  {
    "type": "Domain",
    "value": "microsoftlatamholiday.com"
  },
  {
    "type": "Domain",
    "value": "microsoftmxfilantropia.com"
  },
  {
    "type": "Domain",
    "value": "microsoftpartnersolutions.com"
  },
  {
    "type": "Domain",
    "value": "msunlimitedcloudsummit.com"
  },
  {
    "type": "Domain",
    "value": "office365love.com"
  },
  {
    "type": "Domain",
    "value": "office365tw.com"
  },
  {
    "type": "Domain",
    "value": "renovacionoffice.com"
  },
  {
    "type": "Domain",
    "value": "visualstudio.net"
  },
  {
    "type": "Domain",
    "value": "githubnext.com"
  },
  {
    "type": "Domain",
    "value": "git.io"
  },
  {
    "type": "Domain",
    "value": "atom.io"
  },
  {
    "type": "Domain",
    "value": "ghcr.io"
  },
  {
    "type": "Domain",
    "value": "githubpreview.dev"
  },
  {
    "type": "Domain",
    "value": "github.ai"
  },
  {
    "type": "Domain",
    "value": "github.blog"
  },
  {
    "type": "Domain",
    "value": "github.com"
  },
  {
    "type": "Domain",
    "value": "github.community"
  },
  {
    "type": "Domain",
    "value": "github.dev"
  },
  {
    "type": "Domain",
    "value": "github.io"
  },
  {
    "type": "Domain",
    "value": "githubstatus.com"
  },
  {
    "type": "Domain",
    "value": "githubassets.com"
  },
  {
    "type": "Domain",
    "value": "githubhackathon.com"
  },
  {
    "type": "Domain",
    "value": "gh.io"
  },
  {
    "type": "Domain",
    "value": "dependabot.com"
  },
  {
    "type": "Domain",
    "value": "githubapp.com"
  },
  {
    "type": "Domain",
    "value": "githubuniverse.com"
  },
  {
    "type": "Domain",
    "value": "githubusercontent.com"
  },
  {
    "type": "Domain",
    "value": "myoctocat.com"
  },
  {
    "type": "Domain",
    "value": "octocaptcha.com"
  },
  {
    "type": "Domain",
    "value": "opensource.guide"
  },
  {
    "type": "Domain",
    "value": "repo.new"
  },
  {
    "type": "Domain",
    "value": "thegithubshop.com"
  },
  {
    "type": "Domain",
    "value": "npmjs.org"
  },
  {
    "type": "Domain",
    "value": "githubcopilot.com"
  },
  {
    "type": "Domain",
    "value": "npm.community"
  },
  {
    "type": "Domain",
    "value": "npmjs.com"
  },
  {
    "type": "Domain",
    "value": "visualstudio.eu"
  },
  {
    "type": "Domain",
    "value": "adaptivecards.io"
  },
  {
    "type": "Domain",
    "value": "api-extractor.com"
  },
  {
    "type": "Domain",
    "value": "apisof.net"
  },
  {
    "type": "Domain",
    "value": "appcenter.ms"
  },
  {
    "type": "Domain",
    "value": "blazor.net"
  },
  {
    "type": "Domain",
    "value": "codethemicrobit.com"
  },
  {
    "type": "Domain",
    "value": "devopsassessment.net"
  },
  {
    "type": "Domain",
    "value": "dot.net"
  },
  {
    "type": "Domain",
    "value": "gamesstack.com"
  },
  {
    "type": "Domain",
    "value": "graphengine.io"
  },
  {
    "type": "Domain",
    "value": "insiderdevtour.com"
  },
  {
    "type": "Domain",
    "value": "jwt.ms"
  },
  {
    "type": "Domain",
    "value": "microbit.org"
  },
  {
    "type": "Domain",
    "value": "microsoftadc.com"
  },
  {
    "type": "Domain",
    "value": "microsoftgamestack.com"
  },
  {
    "type": "Domain",
    "value": "microsoftiotinsiderlabs.com"
  },
  {
    "type": "Domain",
    "value": "microsoftreactor.info"
  },
  {
    "type": "Domain",
    "value": "microsoftreactor.net"
  },
  {
    "type": "Domain",
    "value": "microsoftreactor.org"
  },
  {
    "type": "Domain",
    "value": "microsoftsilverlight.com"
  },
  {
    "type": "Domain",
    "value": "microsoftsilverlight.org"
  },
  {
    "type": "Domain",
    "value": "microsoftsilverlight.net"
  },
  {
    "type": "Domain",
    "value": "microsoftsqlserver.com"
  },
  {
    "type": "Domain",
    "value": "mmdnn.com"
  },
  {
    "type": "Domain",
    "value": "mono-project.com"
  },
  {
    "type": "Domain",
    "value": "msdn.com"
  },
  {
    "type": "Domain",
    "value": "msinnovationchallenge.com"
  },
  {
    "type": "Domain",
    "value": "mspairlift.com"
  },
  {
    "type": "Domain",
    "value": "msropendata.com"
  },
  {
    "type": "Domain",
    "value": "nuget.org"
  },
  {
    "type": "Domain",
    "value": "nugettest.org"
  },
  {
    "type": "Domain",
    "value": "opentranslatorstothings.org"
  },
  {
    "type": "Domain",
    "value": "poshtestgallery.com"
  },
  {
    "type": "Domain",
    "value": "pwabuilder.com"
  },
  {
    "type": "Domain",
    "value": "sankie.net"
  },
  {
    "type": "Domain",
    "value": "sqlserveronlinux.com"
  },
  {
    "type": "Domain",
    "value": "timelinestoryteller.com"
  },
  {
    "type": "Domain",
    "value": "uwpcommunitytoolkit.com"
  },
  {
    "type": "Domain",
    "value": "visualstudio-staging.com"
  },
  {
    "type": "Domain",
    "value": "visualstudio.com"
  },
  {
    "type": "Domain",
    "value": "visualstudio.co"
  },
  {
    "type": "Domain",
    "value": "live.com.au"
  },
  {
    "type": "Domain",
    "value": "onedrive.co.uk"
  },
  {
    "type": "Domain",
    "value": "skypedata.akadns.net"
  },
  {
    "type": "Domain",
    "value": "skype-edf.akadns.net"
  },
  {
    "type": "Domain",
    "value": "microsoftstore.com.hk"
  },
  {
    "type": "Domain",
    "value": "visualstudio.co.uk"
  },
  {
    "type": "Regex",
    "value": "^github-production-release-asset-[0-9a-zA-Z]{6}\\.s3\\.amazonaws\\.com$"
  },
  {
    "type": "Domain",
    "value": "dcg.microsoft.com",
    "attrs": {
      "cn": {
        "BoolValue": true
      }
    }
  },
  {
    "type": "Domain",
    "value": "dynamics.cn",
    "attrs": {
      "cn": {
        "BoolValue": true
      }
    }
  },
  {
    "type": "Domain",
    "value": "engkoo.com",
    "attrs": {
      "cn": {
        "BoolValue": true
      }
    }
  },
  {
    "type": "Domain",
    "value": "lync.cn",
    "attrs": {
      "cn": {
        "BoolValue": true
      }
    }
  },
  {
    "type": "Domain",
    "value": "microsoft-smb.cn",
    "attrs": {
      "cn": {
        "BoolValue": true
      }
    }
  },
  {
    "type": "Domain",
    "value": "microsoftonline-i.cn",
    "attrs": {
      "cn": {
        "BoolValue": true
      }
    }
  },
  {
    "type": "Domain",
    "value": "microsoftonline-m-i.cn",
    "attrs": {
      "cn": {
        "BoolValue": true
      }
    }
  },
  {
    "type": "Domain",
    "value": "microsoftonline-m.cn",
    "attrs": {
      "cn": {
        "BoolValue": true
      }
    }
  },
  {
    "type": "Domain",
    "value": "microsoftonline-p-i.cn",
    "attrs": {
      "cn": {
        "BoolValue": true
      }
    }
  },
  {
    "type": "Domain",
    "value": "microsoftonline-p-i.net.cn",
    "attrs": {
      "cn": {
        "BoolValue": true
      }
    }
  },
  {
    "type": "Domain",
    "value": "microsoftonline-p.cn",
    "attrs": {
      "cn": {
        "BoolValue": true
      }
    }
  },
  {
    "type": "Domain",
    "value": "microsoftonline-p.net.cn",
    "attrs": {
      "cn": {
        "BoolValue": true
      }
    }
  },
  {
    "type": "Domain",
    "value": "microsoftonline.cn",
    "attrs": {
      "cn": {
        "BoolValue": true
      }
    }
  },
  {
    "type": "Domain",
    "value": "microsoftstore.com.cn",
    "attrs": {
      "cn": {
        "BoolValue": true
      }
    }
  },
  {
    "type": "Domain",
    "value": "microsofttranslator-int.cn",
    "attrs": {
      "cn": {
        "BoolValue": true
      }
    }
  },
  {
    "type": "Domain",
    "value": "msauth.cn",
    "attrs": {
      "cn": {
        "BoolValue": true
      }
    }
  },
  {
    "type": "Domain",
    "value": "msauthimages.cn",
    "attrs": {
      "cn": {
        "BoolValue": true
      }
    }
  },
  {
    "type": "Domain",
    "value": "msftauth.cn",
    "attrs": {
      "cn": {
        "BoolValue": true
      }
    }
  },
  {
    "type": "Domain",
    "value": "msftauthimages.cn",
    "attrs": {
      "cn": {
        "BoolValue": true
      }
    }
  },
  {
    "type": "Domain",
    "value": "mspil.cn",
    "attrs": {
      "cn": {
        "BoolValue": true
      }
    }
  },
  {
    "type": "Domain",
    "value": "msra.cn",
    "attrs": {
      "cn": {
        "BoolValue": true
      }
    }
  },
  {
    "type": "Domain",
    "value": "o365cn.com",
    "attrs": {
      "cn": {
        "BoolValue": true
      }
    }
  },
  {
    "type": "Domain",
    "value": "o365files.cn",
    "attrs": {
      "cn": {
        "BoolValue": true
      }
    }
  },
  {
    "type": "Domain",
    "value": "office365-net.cn",
    "attrs": {
      "cn": {
        "BoolValue": true
      }
    }
  },
  {
    "type": "Domain",
    "value": "office365.cn",
    "attrs": {
      "cn": {
        "BoolValue": true
      }
    }
  },
  {
    "type": "Domain",
    "value": "officeplus.cn",
    "attrs": {
      "cn": {
        "BoolValue": true
      }
    }
  },
  {
    "type": "Domain",
    "value": "officewebapps.cn",
    "attrs": {
      "cn": {
        "BoolValue": true
      }
    }
  },
  {
    "type": "Domain",
    "value": "onmschina.cn",
    "attrs": {
      "cn": {
        "BoolValue": true
      }
    }
  },
  {
    "type": "Domain",
    "value": "outlook.cn",
    "attrs": {
      "cn": {
        "BoolValue": true
      }
    }
  },
  {
    "type": "Domain",
    "value": "pbiwebcontent.cn",
    "attrs": {
      "cn": {
        "BoolValue": true
      }
    }
  },
  {
    "type": "Domain",
    "value": "powerapps.cn",
    "attrs": {
      "cn": {
        "BoolValue": true
      }
    }
  },
  {
    "type": "Domain",
    "value": "powerappsportals.cn",
    "attrs": {
      "cn": {
        "BoolValue": true
      }
    }
  },
  {
    "type": "Domain",
    "value": "powerautomate.cn",
    "attrs": {
      "cn": {
        "BoolValue": true
      }
    }
  },
  {
    "type": "Domain",
    "value": "powerbi.cn",
    "attrs": {
      "cn": {
        "BoolValue": true
      }
    }
  },
  {
    "type": "Domain",
    "value": "sharepoint.cn",
    "attrs": {
      "cn": {
        "BoolValue": true
      }
    }
  },
  {
    "type": "Domain",
    "value": "clarity.ms",
    "attrs": {
      "ads": {
        "BoolValue": true
      }
    }
  },
  {
    "type": "Domain",
    "value": "microsoftads.com",
    "attrs": {
      "ads": {
        "BoolValue": true
      }
    }
  },
  {
    "type": "Domain",
    "value": "msads.net",
    "attrs": {
      "ads": {
        "BoolValue": true
      }
    }
  },
  {
    "type": "Domain",
    "value": "nelreports.net",
    "attrs": {
      "ads": {
        "BoolValue": true
      }
    }
  },
  {
    "type": "Domain",
    "value": "dl.delivery.mp.microsoft.com",
    "attrs": {
      "cn": {
        "BoolValue": true
      }
    }
  },
  {
    "type": "Domain",
    "value": "download.windowsupdate.com",
    "attrs": {
      "cn": {
        "BoolValue": true
      }
    }
  },
  {
    "type": "Full",
    "value": "b.c2r.ts.cdn.office.net",
    "attrs": {
      "cn": {
        "BoolValue": true
      }
    }
  },
  {
    "type": "Full",
    "value": "bg.v4.a.dl.ws.microsoft.com",
    "attrs": {
      "cn": {
        "BoolValue": true
      }
    }
  },
  {
    "type": "Full",
    "value": "bg4.v4.a.dl.ws.microsoft.com",
    "attrs": {
      "cn": {
        "BoolValue": true
      }
    }
  },
  {
    "type": "Full",
    "value": "build.microsoft.com",
    "attrs": {
      "cn": {
        "BoolValue": true
      }
    }
  },
  {
    "type": "Full",
    "value": "cdn.marketplaceimages.windowsphone.com",
    "attrs": {
      "cn": {
        "BoolValue": true
      }
    }
  },
  {
    "type": "Full",
    "value": "cn.windowssearch.com",
    "attrs": {
      "cn": {
        "BoolValue": true
      }
    }
  },
  {
    "type": "Full",
    "value": "ctldl.windowsupdate.com",
    "attrs": {
      "cn": {
        "BoolValue": true
      }
    }
  },
  {
    "type": "Full",
    "value": "devblogs.microsoft.com",
    "attrs": {
      "cn": {
        "BoolValue": true
      }
    }
  },
  {
    "type": "Full",
    "value": "developer.microsoft.com",
    "attrs": {
      "cn": {
        "BoolValue": true
      }
    }
  },
  {
    "type": "Full",
    "value": "docs.microsoft.com",
    "attrs": {
      "cn": {
        "BoolValue": true
      }
    }
  },
  {
    "type": "Full",
    "value": "download.microsoft.com",
    "attrs": {
      "cn": {
        "BoolValue": true
      }
    }
  },
  {
    "type": "Full",
    "value": "download.visualstudio.microsoft.com",
    "attrs": {
      "cn": {
        "BoolValue": true
      }
    }
  },
  {
    "type": "Full",
    "value": "f.c2r.ts.cdn.office.net",
    "attrs": {
      "cn": {
        "BoolValue": true
      }
    }
  },
  {
    "type": "Full",
    "value": "fs.microsoft.com",
    "attrs": {
      "cn": {
        "BoolValue": true
      }
    }
  },
  {
    "type": "Full",
    "value": "learn.microsoft.com",
    "attrs": {
      "cn": {
        "BoolValue": true
      }
    }
  },
  {
    "type": "Full",
    "value": "myvs.download.prss.microsoft.com",
    "attrs": {
      "cn": {
        "BoolValue": true
      }
    }
  },
  {
    "type": "Full",
    "value": "oemsoc.download.prss.microsoft.com",
    "attrs": {
      "cn": {
        "BoolValue": true
      }
    }
  },
  {
    "type": "Full",
    "value": "officecdn.microsoft.com",
    "attrs": {
      "cn": {
        "BoolValue": true
      }
    }
  },
  {
    "type": "Full",
    "value": "res-1.cdn.office.net",
    "attrs": {
      "cn": {
        "BoolValue": true
      }
    }
  },
  {
    "type": "Full",
    "value": "res.cdn.office.net",
    "attrs": {
      "cn": {
        "BoolValue": true
      }
    }
  },
  {
    "type": "Full",
    "value": "sdx.microsoft.com",
    "attrs": {
      "cn": {
        "BoolValue": true
      }
    }
  },
  {
    "type": "Full",
    "value": "shell.cdn.office.net",
    "attrs": {
      "cn": {
        "BoolValue": true
      }
    }
  },
  {
    "type": "Full",
    "value": "software.download.prss.microsoft.com",
    "attrs": {
      "cn": {
        "BoolValue": true
      }
    }
  },
  {
    "type": "Full",
    "value": "statics.teams.cdn.office.net",
    "attrs": {
      "cn": {
        "BoolValue": true
      }
    }
  },
  {
    "type": "Full",
    "value": "storeedgefd.dsx.mp.microsoft.com",
    "attrs": {
      "cn": {
        "BoolValue": true
      }
    }
  },
  {
    "type": "Full",
    "value": "surface.downloads.prss.microsoft.com",
    "attrs": {
      "cn": {
        "BoolValue": true
      }
    }
  },
  {
    "type": "Full",
    "value": "vscode.download.prss.microsoft.com",
    "attrs": {
      "cn": {
        "BoolValue": true
      }
    }
  },
  {
    "type": "Full",
    "value": "vz.download.prss.microsoft.com",
    "attrs": {
      "cn": {
        "BoolValue": true
      }
    }
  },
  {
    "type": "Full",
    "value": "wscont1.apps.microsoft.com",
    "attrs": {
      "cn": {
        "BoolValue": true
      }
    }
  },
  {
    "type": "Full",
    "value": "wscont2.apps.microsoft.com",
    "attrs": {
      "cn": {
        "BoolValue": true
      }
    }
  },
  {
    "type": "Full",
    "value": "www.microsoft.com",
    "attrs": {
      "cn": {
        "BoolValue": true
      }
    }
  },
  {
    "type": "Domain",
    "value": "microsoftnews.cn",
    "attrs": {
      "cn": {
        "BoolValue": true
      }
    }
  },
  {
    "type": "Domain",
    "value": "msn.cn",
    "attrs": {
      "cn": {
        "BoolValue": true
      }
    }
  },
  {
    "type": "Domain",
    "value": "browser.events.data.msn.cn",
    "attrs": {
      "ads": {
        "BoolValue": true
      },
      "cn": {
        "BoolValue": true
      }
    }
  },
  {
    "type": "Domain",
    "value": "browser.events.data.msn.com",
    "attrs": {
      "ads": {
        "BoolValue": true
      }
    }
  },
  {
    "type": "Domain",
    "value": "xboxlive.cn",
    "attrs": {
      "cn": {
        "BoolValue": true
      }
    }
  },
  {
    "type": "Domain",
    "value": "21vbc.com",
    "attrs": {
      "cn": {
        "BoolValue": true
      }
    }
  },
  {
    "type": "Domain",
    "value": "21vbluecloud.com",
    "attrs": {
      "cn": {
        "BoolValue": true
      }
    }
  },
  {
    "type": "Domain",
    "value": "21vbluecloud.net",
    "attrs": {
      "cn": {
        "BoolValue": true
      }
    }
  },
  {
    "type": "Domain",
    "value": "aadrm.cn",
    "attrs": {
      "cn": {
        "BoolValue": true
      }
    }
  },
  {
    "type": "Domain",
    "value": "aggresmart.com",
    "attrs": {
      "cn": {
        "BoolValue": true
      }
    }
  },
  {
    "type": "Domain",
    "value": "apihub-internal.cn",
    "attrs": {
      "cn": {
        "BoolValue": true
      }
    }
  },
  {
    "type": "Domain",
    "value": "appserviceenvironment.cn",
    "attrs": {
      "cn": {
        "BoolValue": true
      }
    }
  },
  {
    "type": "Domain",
    "value": "azcrmc-test.cn",
    "attrs": {
      "cn": {
        "BoolValue": true
      }
    }
  },
  {
    "type": "Domain",
    "value": "azcrmc.cn",
    "attrs": {
      "cn": {
        "BoolValue": true
      }
    }
  },
  {
    "type": "Domain",
    "value": "azk8s.cn",
    "attrs": {
      "cn": {
        "BoolValue": true
      }
    }
  },
  {
    "type": "Domain",
    "value": "aznbcontent.cn",
    "attrs": {
      "cn": {
        "BoolValue": true
      }
    }
  },
  {
    "type": "Domain",
    "value": "aztask.cn",
    "attrs": {
      "cn": {
        "BoolValue": true
      }
    }
  },
  {
    "type": "Domain",
    "value": "azure-api.cn",
    "attrs": {
      "cn": {
        "BoolValue": true
      }
    }
  },
  {
    "type": "Domain",
    "value": "azure-apihub.cn",
    "attrs": {
      "cn": {
        "BoolValue": true
      }
    }
  },
  {
    "type": "Domain",
    "value": "azure-automation.cn",
    "attrs": {
      "cn": {
        "BoolValue": true
      }
    }
  },
  {
    "type": "Domain",
    "value": "azure-connectedvehicles-stage.cn",
    "attrs": {
      "cn": {
        "BoolValue": true
      }
    }
  },
  {
    "type": "Domain",
    "value": "azure-connectedvehicles.cn",
    "attrs": {
      "cn": {
        "BoolValue": true
      }
    }
  },
  {
    "type": "Domain",
    "value": "azure-devices-provisioning.cn",
    "attrs": {
      "cn": {
        "BoolValue": true
      }
    }
  },
  {
    "type": "Domain",
    "value": "azure-devices.cn",
    "attrs": {
      "cn": {
        "BoolValue": true
      }
    }
  },
  {
    "type": "Domain",
    "value": "azure.cn",
    "attrs": {
      "cn": {
        "BoolValue": true
      }
    }
  },
  {
    "type": "Domain",
    "value": "azurecr-test.cn",
    "attrs": {
      "cn": {
        "BoolValue": true
      }
    }
  },
  {
    "type": "Domain",
    "value": "azurecr.cn",
    "attrs": {
      "cn": {
        "BoolValue": true
      }
    }
  },
  {
    "type": "Domain",
    "value": "azurehdinsight.cn",
    "attrs": {
      "cn": {
        "BoolValue": true
      }
    }
  },
  {
    "type": "Domain",
    "value": "azureiotsuite.cn",
    "attrs": {
      "cn": {
        "BoolValue": true
      }
    }
  },
  {
    "type": "Domain",
    "value": "azuremresolver.cn",
    "attrs": {
      "cn": {
        "BoolValue": true
      }
    }
  },
  {
    "type": "Domain",
    "value": "azureprivatedns.cn",
    "attrs": {
      "cn": {
        "BoolValue": true
      }
    }
  },
  {
    "type": "Domain",
    "value": "azurerms.cn",
    "attrs": {
      "cn": {
        "BoolValue": true
      }
    }
  },
  {
    "type": "Domain",
    "value": "azuresandbox.cn",
    "attrs": {
      "cn": {
        "BoolValue": true
      }
    }
  },
  {
    "type": "Domain",
    "value": "b2clogin.cn",
    "attrs": {
      "cn": {
        "BoolValue": true
      }
    }
  },
  {
    "type": "Domain",
    "value": "b3itech.cn",
    "attrs": {
      "cn": {
        "BoolValue": true
      }
    }
  },
  {
    "type": "Domain",
    "value": "blueaggrestore.com",
    "attrs": {
      "cn": {
        "BoolValue": true
      }
    }
  },
  {
    "type": "Domain",
    "value": "bluecloudprod.com",
    "attrs": {
      "cn": {
        "BoolValue": true
      }
    }
  },
  {
    "type": "Domain",
    "value": "cegid-cloud.cn",
    "attrs": {
      "cn": {
        "BoolValue": true
      }
    }
  },
  {
    "type": "Domain",
    "value": "chinacloud-mobile.cn",
    "attrs": {
      "cn": {
        "BoolValue": true
      }
    }
  },
  {
    "type": "Domain",
    "value": "chinacloudapi.cn",
    "attrs": {
      "cn": {
        "BoolValue": true
      }
    }
  },
  {
    "type": "Domain",
    "value": "chinacloudapp.cn",
    "attrs": {
      "cn": {
        "BoolValue": true
      }
    }
  },
  {
    "type": "Domain",
    "value": "chinacloudsites.cn",
    "attrs": {
      "cn": {
        "BoolValue": true
      }
    }
  },
  {
    "type": "Domain",
    "value": "hdinsightservices.cn",
    "attrs": {
      "cn": {
        "BoolValue": true
      }
    }
  },
  {
    "type": "Domain",
    "value": "management-azure-devices-provisioning.cn",
    "attrs": {
      "cn": {
        "BoolValue": true
      }
    }
  },
  {
    "type": "Domain",
    "value": "management-azure-devices.cn",
    "attrs": {
      "cn": {
        "BoolValue": true
      }
    }
  },
  {
    "type": "Domain",
    "value": "mcchcdn.com",
    "attrs": {
      "cn": {
        "BoolValue": true
      }
    }
  },
  {
    "type": "Domain",
    "value": "mgmt-azure-api.cn",
    "attrs": {
      "cn": {
        "BoolValue": true
      }
    }
  },
  {
    "type": "Domain",
    "value": "microsoftazurestatus.cn",
    "attrs": {
      "cn": {
        "BoolValue": true
      }
    }
  },
  {
    "type": "Domain",
    "value": "microsoftmetrics.cn",
    "attrs": {
      "cn": {
        "BoolValue": true
      }
    }
  },
  {
    "type": "Domain",
    "value": "mncmsidlab1.cn",
    "attrs": {
      "cn": {
        "BoolValue": true
      }
    }
  },
  {
    "type": "Domain",
    "value": "msappproxy.cn",
    "attrs": {
      "cn": {
        "BoolValue": true
      }
    }
  },
  {
    "type": "Domain",
    "value": "mschcdn.com",
    "attrs": {
      "cn": {
        "BoolValue": true
      }
    }
  },
  {
    "type": "Domain",
    "value": "msftcloudes.cn",
    "attrs": {
      "cn": {
        "BoolValue": true
      }
    }
  },
  {
    "type": "Domain",
    "value": "msidentity.cn",
    "attrs": {
      "cn": {
        "BoolValue": true
      }
    }
  },
  {
    "type": "Domain",
    "value": "msidlabpbmc.cn",
    "attrs": {
      "cn": {
        "BoolValue": true
      }
    }
  },
  {
    "type": "Domain",
    "value": "trafficmanager.cn",
    "attrs": {
      "cn": {
        "BoolValue": true
      }
    }
  },
  {
    "type": "Domain",
    "value": "trustcenter.cn",
    "attrs": {
      "cn": {
        "BoolValue": true
      }
    }
  },
  {
    "type": "Domain",
    "value": "unity3dcloud.cn",
    "attrs": {
      "cn": {
        "BoolValue": true
      }
    }
  },
  {
    "type": "Domain",
    "value": "windowsazure.cn",
    "attrs": {
      "cn": {
        "BoolValue": true
      }
    }
  },
  {
    "type": "Domain",
    "value": "windowsazurestatus.cn",
    "attrs": {
      "cn": {
        "BoolValue": true
      }
    }
  },
  {
    "type": "Domain",
    "value": "azchcdna.com",
    "attrs": {
      "cn": {
        "BoolValue": true
      }
    }
  },
  {
    "type": "Domain",
    "value": "azchcdnb.com",
    "attrs": {
      "cn": {
        "BoolValue": true
      }
    }
  },
  {
    "type": "Domain",
    "value": "azchcdnc.com",
    "attrs": {
      "cn": {
        "BoolValue": true
      }
    }
  },
  {
    "type": "Domain",
    "value": "azchcdnd.com",
    "attrs": {
      "cn": {
        "BoolValue": true
      }
    }
  },
  {
    "type": "Domain",
    "value": "azchcdne.com",
    "attrs": {
      "cn": {
        "BoolValue": true
      }
    }
  },
  {
    "type": "Domain",
    "value": "azchcdnf.com",
    "attrs": {
      "cn": {
        "BoolValue": true
      }
    }
  },
  {
    "type": "Domain",
    "value": "azchcdng.com",
    "attrs": {
      "cn": {
        "BoolValue": true
      }
    }
  },
  {
    "type": "Domain",
    "value": "azchcdnh.com",
    "attrs": {
      "cn": {
        "BoolValue": true
      }
    }
  },
  {
    "type": "Domain",
    "value": "azchcdni.com",
    "attrs": {
      "cn": {
        "BoolValue": true
      }
    }
  },
  {
    "type": "Domain",
    "value": "azchcdnj.com",
    "attrs": {
      "cn": {
        "BoolValue": true
      }
    }
  },
  {
    "type": "Domain",
    "value": "azchcdnk.com",
    "attrs": {
      "cn": {
        "BoolValue": true
      }
    }
  },
  {
    "type": "Domain",
    "value": "azchcdnl.com",
    "attrs": {
      "cn": {
        "BoolValue": true
      }
    }
  },
  {
    "type": "Domain",
    "value": "azchcdnm.com",
    "attrs": {
      "cn": {
        "BoolValue": true
      }
    }
  },
  {
    "type": "Domain",
    "value": "azchcdnn.com",
    "attrs": {
      "cn": {
        "BoolValue": true
      }
    }
  },
  {
    "type": "Domain",
    "value": "azchcdno.com",
    "attrs": {
      "cn": {
        "BoolValue": true
      }
    }
  },
  {
    "type": "Domain",
    "value": "azchcdnp.com",
    "attrs": {
      "cn": {
        "BoolValue": true
      }
    }
  },
  {
    "type": "Domain",
    "value": "azchcdnq.com",
    "attrs": {
      "cn": {
        "BoolValue": true
      }
    }
  },
  {
    "type": "Domain",
    "value": "azchcdnr.com",
    "attrs": {
      "cn": {
        "BoolValue": true
      }
    }
  },
  {
    "type": "Domain",
    "value": "azchcdns.com",
    "attrs": {
      "cn": {
        "BoolValue": true
      }
    }
  },
  {
    "type": "Domain",
    "value": "azure-dns.cn",
    "attrs": {
      "cn": {
        "BoolValue": true
      }
    }
  },
  {
    "type": "Domain",
    "value": "azure-dns-1.cn",
    "attrs": {
      "cn": {
        "BoolValue": true
      }
    }
  },
  {
    "type": "Domain",
    "value": "azure-dns-2.cn",
    "attrs": {
      "cn": {
        "BoolValue": true
      }
    }
  },
  {
    "type": "Domain",
    "value": "azure-dns-3.cn",
    "attrs": {
      "cn": {
        "BoolValue": true
      }
    }
  },
  {
    "type": "Domain",
    "value": "azure-dns-4.cn",
    "attrs": {
      "cn": {
        "BoolValue": true
      }
    }
  },
  {
    "type": "Domain",
    "value": "azure-dns-5.cn",
    "attrs": {
      "cn": {
        "BoolValue": true
      }
    }
  },
  {
    "type": "Domain",
    "value": "azure-dns-6.cn",
    "attrs": {
      "cn": {
        "BoolValue": true
      }
    }
  },
  {
    "type": "Domain",
    "value": "azure-dns-7.cn",
    "attrs": {
      "cn": {
        "BoolValue": true
      }
    }
  },
  {
    "type": "Domain",
    "value": "azure-dns-8.cn",
    "attrs": {
      "cn": {
        "BoolValue": true
      }
    }
  },
  {
    "type": "Domain",
    "value": "azure-dns-9.cn",
    "attrs": {
      "cn": {
        "BoolValue": true
      }
    }
  },
  {
    "type": "Domain",
    "value": "azure-dns-10.cn",
    "attrs": {
      "cn": {
        "BoolValue": true
      }
    }
  },
  {
    "type": "Domain",
    "value": "bing.com.cn",
    "attrs": {
      "cn": {
        "BoolValue": true
      }
    }
  },
  {
    "type": "Domain",
    "value": "bingads.com",
    "attrs": {
      "ads": {
        "BoolValue": true
      }
    }
  },
  {
    "type": "Domain",
    "value": "cn.bing.com",
    "attrs": {
      "cn": {
        "BoolValue": true
      }
    }
  },
  {
    "type": "Domain",
    "value": "cn.bing.net",
    "attrs": {
      "cn": {
        "BoolValue": true
      }
    }
  },
  {
    "type": "Domain",
    "value": "cn.mm.bing.net",
    "attrs": {
      "cn": {
        "BoolValue": true
      }
    }
  },
  {
    "type": "Domain",
    "value": "ditu.live.com",
    "attrs": {
      "cn": {
        "BoolValue": true
      }
    }
  },
  {
    "type": "Domain",
    "value": "r.bing.com",
    "attrs": {
      "cn": {
        "BoolValue": true
      }
    }
  },
  {
    "type": "Domain",
    "value": "th.bing.com",
    "attrs": {
      "cn": {
        "BoolValue": true
      }
    }
  },
  {
    "type": "Full",
    "value": "bj1.api.bing.com",
    "attrs": {
      "cn": {
        "BoolValue": true
      }
    }
  },
  {
    "type": "Full",
    "value": "emoi-cncdn.bing.com",
    "attrs": {
      "cn": {
        "BoolValue": true
      }
    }
  },
  {
    "type": "Domain",
    "value": "collector.github.com",
    "attrs": {
      "ads": {
        "BoolValue": true
      }
    }
  },
  {
    "type": "Domain",
    "value": "copilot-telemetry.githubusercontent.com",
    "attrs": {
      "ads": {
        "BoolValue": true
      }
    }
  },
  {
    "type": "Domain",
    "value": "microsoftreactor.cn",
    "attrs": {
      "cn": {
        "BoolValue": true
      }
    }
  },
  {
    "type": "Domain",
    "value": "microsoftreactor.com.cn",
    "attrs": {
      "cn": {
        "BoolValue": true
      }
    }
  },
  {
    "type": "Domain",
    "value": "reactorms.com.cn",
    "attrs": {
      "cn": {
        "BoolValue": true
      }
    }
  }
]