[
  {
    "type": "Domain",
    "value": "naver.com"
  },
  {
    "type": "Domain",
    "value": "naver.me"
  },
  {
    "type": "Domain",
    "value": "naver.net"
  },
  {
    "type": "Domain",
    "value": "navercorp.com"
  },
  {
    "type": "Domain",
    "value": "nheos.com"
  },
  {
    "type": "Domain",
    "value": "pstatic.net"
  },
  {
    "type": "Domain",
    "value": "clova.ai"
  },
  {
    "type": "Domain",
    "value": "navercloudcorp.com"
  },
  {
    "type": "Domain",
    "value": "naverncp.com"
  },
  {
    "type": "Domain",
    "value": "ncloud.com"
  },
  {
    "type": "Domain",
    "value": "worksmobile.com"
  },
  {
    "type": "Domain",
    "value": "naverfincorp.com"
  },
  {
    "type": "Domain",
    "value": "snow.me"
  },
  {
    "type": "Domain",
    "value": "snowcorp.com"
  },
  {
    "type": "Domain",
    "value": "vday.io"
  },
  {
    "type": "Domain",
    "value": "studiolico.com"
  },
  {
    "type": "Domain",
    "value": "studioncorp.com"
  },
  {
    "type": "Domain",
    "value": "wattpad.com"
  },
  {
    "type": "Domain",
    "value": "webtoons.com"
  },
  {
    "type": "Domain",
    "value": "webtoonscorp.com"
  },
  {
    "type": "Domain",
    "value": "band.us"
  },
  {
    "type": "Domain",
    "value": "grafolio.com"
  },
  {
    "type": "Domain",
    "value": "modoo.at"
  },
  {
    "type": "Domain",
    "value": "naver.jp"
  },
  {
    "type": "Domain",
    "value": "naverads.com"
  },
  {
    "type": "Domain",
    "value": "naverlabs.com"
  },
  {
    "type": "Domain",
    "value": "plug.game"
  },
  {
    "type": "Domain",
    "value": "prismlive.com"
  },
  {
    "type": "Domain",
    "value": "linemobile.com"
  },
  {
    "type": "Domain",
    "value": "lineshoppingseller.com"
  },
  {
    "type": "Domain",
    "value": "line-apps-beta.com"
  },
  {
    "type": "Domain",
    "value": "line-apps-rc.com"
  },
  {
    "type": "Domain",
    "value": "line-apps.com"
  },
  {
    "type": "Domain",
    "value": "line-beta.me"
  },
  {
    "type": "Domain",
    "value": "line-cdn.net"
  },
  {
    "type": "Domain",
    "value": "line.biz"
  },
  {
    "type": "Domain",
    "value": "nhncorp.jp"
  },
  {
    "type": "Domain",
    "value": "lin.ee"
  },
  {
    "type": "Domain",
    "value": "line-scdn.net"
  },
  {
    "type": "Domain",
    "value": "linecorp.com"
  },
  {
    "type": "Domain",
    "value": "linefriends.com"
  },
  {
    "type": "Domain",
    "value": "linetv.tw"
  },
  {
    "type": "Domain",
    "value": "linegame.jp"
  },
  {
    "type": "Domain",
    "value": "gcld-line.com"
  },
  {
    "type": "Domain",
    "value": "linemyshop.com"
  },
  {
    "type": "Domain",
    "value": "line.me"
  },
  {
    "type": "Domain",
    "value": "linefriends.com.tw"
  },
  {
    "type": "Domain",
    "value": "naver.com.akadns.net"
  },
  {
    "type": "Domain",
    "value": "naverads.com.akadns.net"
  }
]