[
  {
    "type": "Domain",
    "value": "softbank"
  },
  {
    "type": "Domain",
    "value": "sb-mobile.jp"
  },
  {
    "type": "Domain",
    "value": "sb-telecom.net"
  },
  {
    "type": "Domain",
    "value": "softbank-ipo.com"
  },
  {
    "type": "Domain",
    "value": "softbank-jp.com"
  },
  {
    "type": "Domain",
    "value": "softbank-robotics.com"
  },
  {
    "type": "Domain",
    "value": "softbank-telecom.com"
  },
  {
    "type": "Domain",
    "value": "softbank-telecom.net"
  },
  {
    "type": "Domain",
    "value": "softbank.jp"
  },
  {
    "type": "Domain",
    "value": "softbank.tv"
  },
  {
    "type": "Domain",
    "value": "softbankbb.com"
  },
  {
    "type": "Domain",
    "value": "softbankbb.net"
  },
  {
    "type": "Domain",
    "value": "softbankci.com"
  },
  {
    "type": "Domain",
    "value": "softbankhawksstore.jp"
  },
  {
    "type": "Domain",
    "value": "softbankmobile.net"
  },
  {
    "type": "Domain",
    "value": "softbankrobotics.com"
  },
  {
    "type": "Domain",
    "value": "softbanktelecom.com"
  },
  {
    "type": "Domain",
    "value": "softbankusa.net"
  },
  {
    "type": "Domain",
    "value": "softbankventuresasia.com"
  },
  {
    "type": "Domain",
    "value": "softbankworld.com"
  }
]