[
  {
    "type": "Full",
    "value": "zeenews-fonts.s3.amazonaws.com"
  },
  {
    "type": "Domain",
    "value": "bgr.in"
  },
  {
    "type": "Domain",
    "value": "bollywoodlife.com"
  },
  {
    "type": "Domain",
    "value": "careerfundas.com"
  },
  {
    "type": "Domain",
    "value": "cricketcountry.com"
  },
  {
    "type": "Domain",
    "value": "dnai.in"
  },
  {
    "type": "Domain",
    "value": "dnaindia.com"
  },
  {
    "type": "Domain",
    "value": "earngeek.com"
  },
  {
    "type": "Domain",
    "value": "ekhindi.com"
  },
  {
    "type": "Domain",
    "value": "ind.sh"
  },
  {
    "type": "Domain",
    "value": "india.com"
  },
  {
    "type": "Domain",
    "value": "indiancolleges.com"
  },
  {
    "type": "Domain",
    "value": "itripto.com"
  },
  {
    "type": "Domain",
    "value": "oncars.in"
  },
  {
    "type": "Domain",
    "value": "prepsure.com"
  },
  {
    "type": "Domain",
    "value": "thehealthsite.com"
  },
  {
    "type": "Domain",
    "value": "wionews.com"
  },
  {
    "type": "Domain",
    "value": "yo1health.com"
  },
  {
    "type": "Domain",
    "value": "zee.com"
  },
  {
    "type": "Domain",
    "value": "zeebiz.com"
  },
  {
    "type": "Domain",
    "value": "zeeentertainment.com"
  },
  {
    "type": "Domain",
    "value": "zeenews.com"
  }
]